Metadata-Version: 2.1
Name: HPrIm
Version: 0.1
Summary: Herramientas para el Procesamiento de Imágenes
Home-page: https://github.com/nakato156/HPrIm
Author: Nakato
Author-email: nnakato150@gmail.com
Keywords: file,files,text
Requires: numpy
